{
  "r": 0,
  "res": {
    "TYPE": "ActivityPageWidget",
    "comment_count": 25,
    "id": 860,
    "kind": 1,
    "kind_cn": "Top 10",
    "kind_str": "top10",
    "page_id": 15,
    "payload": {
      "background_color": "rgba(54, 71, 81, 0.8)",
      "background_img": "https://img1.doubanio.com/view/activity_page/raw/public/p3357.jpg",
      "description": "\u4ece\u52a8\u7269\u8eab\u4e0a\uff0c\u6211\u4eec\u7167\u89c1\u4e86\u4eba\u7c7b\u539f\u59cb\u7684\u517d\u6027\uff0c\u5373\u4fbf\u662f\u6240\u8c13\u300c\u6587\u660e\u300d\uff0c\u4e5f\u5e76\u975e\u662f\u667a\u4eba\u7684\u72ec\u7279\u4ea7\u7269\u3002",
      "has_barrage": "on",
      "left": "off",
      "mobile_background_img": "https://img3.doubanio.com/view/activity_page/raw/public/p3446.jpg",
      "subject_ids": "27182707, 27620913, 27620616, 27182720, 30156039, 27186602, 30151530, 26955451, 30244576, 26692442",
      "title": "2018\u8bc4\u5206\u6700\u9ad8\u7684\u7eaa\u5f55\u5267\u96c6",
      "user_id": "172680115"
    },
    "status": 0,
    "subject": {
      "color_scheme": {
        "_avg_color": [
          0.5694444444444445,
          0.2790697674418605,
          0.16862745098039217
        ],
        "_base_color": [
          0.5740740740740741,
          0.6206896551724138,
          0.11372549019607843
        ],
        "is_dark": true,
        "primary_color_dark": "1d374c",
        "primary_color_light": "2b5372",
        "secondary_color": "f4f7f9"
      },
      "cover": "https://img1.doubanio.com/view/photo/s_ratio_poster/public/p2537688397.jpg",
      "directors": [
        "\u65af\u8482\u82ac\u00b7\u83ab\u65af Stephen Moss"
      ],
      "id": "27182707",
      "interest": {},
      "is_released": true,
      "m_url": "https://m.douban.com/movie/subject/27182707/",
      "orig_title": "Dynasties",
      "playable": true,
      "rating": 9.6,
      "rating_count": 21809,
      "rating_stats": [
        0.0012838736301526892,
        0.0011921683708560687,
        0.01925810445229034,
        0.14723279380072446,
        0.8310330597459764
      ],
      "title": "\u738b\u671d",
      "type": "movie",
      "url": "https://movie.douban.com/subject/27182707/"
    },
    "subjects": [
      {
        "color_scheme": {
          "_avg_color": [
            0.5694444444444445,
            0.2790697674418605,
            0.16862745098039217
          ],
          "_base_color": [
            0.5740740740740741,
            0.6206896551724138,
            0.11372549019607843
          ],
          "is_dark": true,
          "primary_color_dark": "1d374c",
          "primary_color_light": "2b5372",
          "secondary_color": "f4f7f9"
        },
        "cover": "https://img1.doubanio.com/view/photo/s_ratio_poster/public/p2537688397.jpg",
        "id": "27182707",
        "interest": {},
        "is_released": true,
        "m_url": "https://m.douban.com/movie/subject/27182707/",
        "orig_title": "Dynasties",
        "playable": true,
        "rating": 9.6,
        "rating_count": 21809,
        "rating_stats": [
          0.0012838736301526892,
          0.0011921683708560687,
          0.01925810445229034,
          0.14723279380072446,
          0.8310330597459764
        ],
        "title": "\u738b\u671d",
        "type": "movie",
        "url": "https://movie.douban.com/subject/27182707/"
      },
      {
        "color_scheme": {
          "_avg_color": [
            0.5555555555555557,
            0.16810344827586207,
            0.9098039215686274
          ],
          "_base_color": [
            0.08585858585858586,
            0.1422413793103448,
            0.9098039215686274
          ],
          "is_dark": false,
          "primary_color_dark": "f2e1cf",
          "primary_color_light": "f2e1cf",
          "secondary_color": "f9f7f4"
        },
        "cover": "https://img3.doubanio.com/view/photo/s_ratio_poster/public/p2529397321.jpg",
        "id": "27620913",
        "interest": {},
        "is_released": true,
        "m_url": "https://m.douban.com/movie/subject/27620913/",
        "orig_title": "",
        "playable": true,
        "rating": 9.5,
        "rating_count": 6195,
        "rating_stats": [
          0.00516545601291364,
          0.0017756255044390637,
          0.023728813559322035,
          0.1493139628732849,
          0.8200161420500404
        ],
        "title": "\u5982\u679c\u56fd\u5b9d\u4f1a\u8bf4\u8bdd \u7b2c\u4e8c\u5b63",
        "type": "movie",
        "url": "https://movie.douban.com/subject/27620913/"
      },
      {
        "color_scheme": {
          "_avg_color": [
            0.10666666666666669,
            0.5,
            0.39215686274509803
          ],
          "_base_color": [
            0.1150793650793651,
            0.6176470588235294,
            0.26666666666666666
          ],
          "is_dark": true,
          "primary_color_dark": "4c3d1d",
          "primary_color_light": "725c2b",
          "secondary_color": "f9f8f4"
        },
        "cover": "https://img3.doubanio.com/view/photo/s_ratio_poster/public/p2515345924.jpg",
        "id": "27620616",
        "interest": {},
        "is_released": true,
        "m_url": "https://m.douban.com/movie/subject/27620616/",
        "orig_title": "Big Cats",
        "playable": true,
        "rating": 9.5,
        "rating_count": 14543,
        "rating_stats": [
          0.0006188544316853469,
          0.0016502784844942583,
          0.035549749020147146,
          0.2004400742625318,
          0.7617410438011415
        ],
        "title": "\u5927\u732b",
        "type": "movie",
        "url": "https://movie.douban.com/subject/27620616/"
      },
      {
        "color_scheme": {
          "_avg_color": [
            0.572463768115942,
            0.4539473684210526,
            0.596078431372549
          ],
          "_base_color": [
            0.5717299578059071,
            0.5096774193548387,
            0.6078431372549019
          ],
          "is_dark": true,
          "primary_color_dark": "3e637f",
          "primary_color_light": "5181a5",
          "secondary_color": "f4f7f9"
        },
        "cover": "https://img3.doubanio.com/view/photo/s_ratio_poster/public/p2508653411.jpg",
        "id": "27182720",
        "interest": {},
        "is_released": true,
        "m_url": "https://m.douban.com/movie/subject/27182720/",
        "orig_title": "",
        "playable": true,
        "rating": 9.4,
        "rating_count": 11133,
        "rating_stats": [
          0.002155753166262463,
          0.002784514506422348,
          0.029821252133297404,
          0.17479565256444804,
          0.7904428276295697
        ],
        "title": "\u5982\u679c\u56fd\u5b9d\u4f1a\u8bf4\u8bdd \u7b2c\u4e00\u5b63",
        "type": "movie",
        "url": "https://movie.douban.com/subject/27182720/"
      },
      {
        "color_scheme": {
          "_avg_color": [
            0.5190476190476191,
            0.2317880794701987,
            0.592156862745098
          ],
          "_base_color": [
            0.5266666666666667,
            0.267379679144385,
            0.7333333333333333
          ],
          "is_dark": true,
          "primary_color_dark": "5d7a7f",
          "primary_color_light": "799ea5",
          "secondary_color": "f4f9f9"
        },
        "cover": "https://img3.doubanio.com/view/photo/s_ratio_poster/public/p2541649132.jpg",
        "id": "30156039",
        "interest": {},
        "is_released": true,
        "m_url": "https://m.douban.com/movie/subject/30156039/",
        "orig_title": "",
        "playable": true,
        "rating": 9.1,
        "rating_count": 77657,
        "rating_stats": [
          0.002459533590017642,
          0.003991913156573136,
          0.04667962965347618,
          0.24713805580952136,
          0.6997308677904117
        ],
        "title": "\u98ce\u5473\u4eba\u95f4",
        "type": "movie",
        "url": "https://movie.douban.com/subject/30156039/"
      },
      {
        "color_scheme": {
          "_avg_color": [
            0.8999999999999998,
            0.049751243781094495,
            0.788235294117647
          ],
          "_base_color": [
            0.5817610062893083,
            0.5247524752475248,
            0.396078431372549
          ],
          "is_dark": true,
          "primary_color_dark": "3c5e7f",
          "primary_color_light": "4e7ba5",
          "secondary_color": "f4f7f9"
        },
        "cover": "https://img3.doubanio.com/view/photo/s_ratio_poster/public/p2516431363.jpg",
        "id": "27186602",
        "interest": {},
        "is_released": true,
        "m_url": "https://m.douban.com/movie/subject/27186602/",
        "orig_title": "",
        "playable": true,
        "rating": 9.3,
        "rating_count": 4952,
        "rating_stats": [
          0.0024232633279483036,
          0.0014135702746365104,
          0.027665589660743135,
          0.20860258481421648,
          0.7598949919224556
        ],
        "title": "\u751f\u547d\u65f6\u901f\u00b7\u7d27\u6025\u6551\u62a4120",
        "type": "movie",
        "url": "https://movie.douban.com/subject/27186602/"
      },
      {
        "color_scheme": {
          "_avg_color": [
            0.6190476190476192,
            0.044585987261146515,
            0.615686274509804
          ],
          "_base_color": [
            0.6250000000000003,
            0.02116402116402124,
            0.7411764705882353
          ],
          "is_dark": true,
          "primary_color_dark": "7c7d7f",
          "primary_color_light": "a2a3a5",
          "secondary_color": "f4f6f9"
        },
        "cover": "https://img1.doubanio.com/view/photo/s_ratio_poster/public/p2539266159.jpg",
        "id": "30151530",
        "interest": {},
        "is_released": true,
        "m_url": "https://m.douban.com/movie/subject/30151530/",
        "orig_title": "",
        "playable": true,
        "rating": 9.3,
        "rating_count": 13161,
        "rating_stats": [
          0.0012916951599422537,
          0.0018235696375655346,
          0.030772737633918395,
          0.1951979332877441,
          0.7709140642808298
        ],
        "title": "\u897f\u5357\u8054\u5927",
        "type": "movie",
        "url": "https://movie.douban.com/subject/30151530/"
      },
      {
        "color_scheme": {
          "_avg_color": [
            0.578125,
            0.47761194029850745,
            0.2627450980392157
          ],
          "_base_color": [
            0.5802469135802469,
            0.6428571428571429,
            0.16470588235294117
          ],
          "is_dark": true,
          "primary_color_dark": "1b344c",
          "primary_color_light": "284f72",
          "secondary_color": "f4f7f9"
        },
        "cover": "https://img3.doubanio.com/view/photo/s_ratio_poster/public/p2523480904.jpg",
        "id": "26955451",
        "interest": {},
        "is_released": true,
        "m_url": "https://m.douban.com/movie/subject/26955451/",
        "orig_title": "James Cameron's Story of Science Fiction",
        "playable": false,
        "rating": 9.2,
        "rating_count": 6921,
        "rating_stats": [
          0.003178731397196937,
          0.006212975003612195,
          0.06198526224534027,
          0.2657130472475076,
          0.662909984106343
        ],
        "title": "\u8a79\u59c6\u65af\u00b7\u5361\u6885\u9686\u7684\u79d1\u5e7b\u6545\u4e8b",
        "type": "movie",
        "url": "https://movie.douban.com/subject/26955451/"
      },
      {
        "color_scheme": {
          "_avg_color": [
            0.09999999999999994,
            0.13698630136986292,
            0.28627450980392155
          ],
          "_base_color": [
            0.0,
            0.0,
            0.13333333333333333
          ],
          "is_dark": true,
          "primary_color_dark": "4c4c4c",
          "primary_color_light": "727272",
          "secondary_color": "f9f4f4"
        },
        "cover": "https://img3.doubanio.com/view/photo/s_ratio_poster/public/p2525545214.jpg",
        "id": "30244576",
        "interest": {},
        "is_released": true,
        "m_url": "https://m.douban.com/movie/subject/30244576/",
        "orig_title": "Snatches: Moments from Women's Lives",
        "playable": false,
        "rating": 9.2,
        "rating_count": 5064,
        "rating_stats": [
          0.004739336492890996,
          0.005529225908372828,
          0.054699842022116904,
          0.280608214849921,
          0.6544233807266983
        ],
        "title": "\u5979\u8bf4\uff1a\u5973\u6027\u4eba\u751f\u77ac\u95f4",
        "type": "movie",
        "url": "https://movie.douban.com/subject/30244576/"
      },
      {
        "color_scheme": {
          "_avg_color": [
            0.1011904761904762,
            0.4375,
            0.25098039215686274
          ],
          "_base_color": [
            0.05555555555555556,
            0.631578947368421,
            0.7450980392156863
          ],
          "is_dark": true,
          "primary_color_dark": "4c2c1c",
          "primary_color_light": "72422a",
          "secondary_color": "f9f6f4"
        },
        "cover": "https://img3.doubanio.com/view/photo/s_ratio_poster/public/p2518733754.jpg",
        "id": "26692442",
        "interest": {},
        "is_released": true,
        "m_url": "https://m.douban.com/movie/subject/26692442/",
        "orig_title": "Civilisations",
        "playable": true,
        "rating": 9.1,
        "rating_count": 4441,
        "rating_stats": [
          0.007430758838099527,
          0.009457329430308489,
          0.06575095699166854,
          0.26120243188471065,
          0.6561585228552128
        ],
        "title": "\u6587\u660e",
        "type": "movie",
        "url": "https://movie.douban.com/subject/26692442/"
      }
    ],
    "user": {
      "avatar": "https://img3.doubanio.com/icon/u172680115-3.jpg",
      "id": "172680115",
      "name": "Zucchini",
      "url": "https://www.douban.com/people/172680115/"
    }
  },
  "status": {
    "code": 200
  }
}